limittar/__init__.py
limittar/__main__.py
limittar-1.0.4.dist-info/METADATA
limittar-1.0.4.dist-info/RECORD
limittar-1.0.4.dist-info/WHEEL
limittar-1.0.4.dist-info/entry_points.txt
limittar-1.0.4.dist-info/top_level.txt
