Metadata-Version: 2.1
Name: limittar
Version: 1.0.4
Summary: Limiting the size of tar archives
Home-page: https://github.com/2sh/limittar
Author: Seán Hewitt
Author-email: contact@2sh.me
License: UNKNOWN
Platform: UNKNOWN
Classifier: Programming Language :: Python :: 3
Classifier: License :: OSI Approved :: GNU General Public License v3 or later (GPLv3+)
Classifier: Operating System :: OS Independent
Classifier: Topic :: System :: Archiving
Requires-Python: >=3.4
